csvdata_importer/__init__.py
csvdata_importer/importer.py
csvdata_importer/mapping.py
csvdata_importer/py.typed
csvddata_importer-0.1.0.dist-info/LICENSE
csvddata_importer-0.1.0.dist-info/METADATA
csvddata_importer-0.1.0.dist-info/WHEEL
csvddata_importer-0.1.0.dist-info/top_level.txt
csvddata_importer-0.1.0.dist-info/RECORD
