Metadata-Version: 2.1
Name: csvddata-importer
Version: 0.1.0
Summary: Supports importing files to a database using a mapping configuration.
Author-email: Ernan <ernan@outlook.com>
License: MIT License
Project-URL: Homepage, https://github.com/ernan/csvdata-importer
Classifier: Programming Language :: Python :: 3
Classifier: Operating System :: OS Independent
Classifier: Development Status :: 3 - Alpha
Classifier: License :: OSI Approved :: MIT License
Requires-Python: >=3.11
License-File: LICENSE
Requires-Dist: pandas
Requires-Dist: pytest
Requires-Dist: psycopg2
Requires-Dist: SQLAlchemy
